capitulo_10/__init__.py
capitulo_10/augmented_reality_piramide.py
capitulo_10/pose_estimation.py
capitulo_10/ventana.py
capitulo_6/__init__.py
capitulo_6/expand_image_by_seam_carving.py
capitulo_6/reduce_image_by_seam_carving.py
capitulo_6/remove_element_by_seam_carving.py
capitulo_6/ventana.py
capitulo_7/__init__.py
capitulo_7/censor_shapes.py
capitulo_7/convexity_defects.py
capitulo_7/image_segmentation.py
capitulo_7/smoothen_contour_polygon.py
capitulo_7/ventana.py
capitulo_7/watershed.py
capitulo_8/__init__.py
capitulo_8/background_subtraction_GMG.py
capitulo_8/background_subtraction_MOG.py
capitulo_8/colorspace_tracking.py
capitulo_8/feature_tracking.py
capitulo_8/object_tracker.py
capitulo_8/ventana.py
capitulos_opencv-1.0.0.dist-info/METADATA
capitulos_opencv-1.0.0.dist-info/WHEEL
capitulos_opencv-1.0.0.dist-info/top_level.txt
capitulos_opencv-1.0.0.dist-info/RECORD
