Metadata-Version: 2.1
Name: capitulos-opencv
Version: 1.0.0
Summary: Trabajo universitario
Home-page: 
Author: Gerson Pulache
Author-email: pulachegerson@gmail.com
